codat_lending/__init__.py
codat_lending/_hooks/__init__.py
codat_lending/_hooks/registration.py
codat_lending/_hooks/sdkhooks.py
codat_lending/_hooks/types.py
codat_lending/_version.py
codat_lending/account_balances.py
codat_lending/account_transactions.py
codat_lending/accounts.py
codat_lending/accounts_payable.py
codat_lending/accounts_receivable.py
codat_lending/balance_sheet.py
codat_lending/bank_accounts.py
codat_lending/bank_statements.py
codat_lending/bank_transactions.py
codat_lending/banking.py
codat_lending/basesdk.py
codat_lending/bill_credit_notes.py
codat_lending/bill_payments.py
codat_lending/bills.py
codat_lending/cash_flow.py
codat_lending/categorized_statement.py
codat_lending/codatlending_accounting_bank_data.py
codat_lending/codatlending_accounts.py
codat_lending/codatlending_banking_transactions.py
codat_lending/codatlending_customers.py
codat_lending/codatlending_direct_costs.py
codat_lending/codatlending_financial_statements_accounts.py
codat_lending/codatlending_loan_writeback_accounts.py
codat_lending/codatlending_payments.py
codat_lending/codatlending_reports.py
codat_lending/codatlending_sales_payments.py
codat_lending/codatlending_suppliers.py
codat_lending/codatlending_transactions.py
codat_lending/codatlending_transfers.py
codat_lending/companies.py
codat_lending/company_info.py
codat_lending/connections.py
codat_lending/create_operations.py
codat_lending/credit_notes.py
codat_lending/customers.py
codat_lending/data_integrity.py
codat_lending/direct_costs.py
codat_lending/direct_incomes.py
codat_lending/disputes.py
codat_lending/excel_reports.py
codat_lending/file_upload.py
codat_lending/financial_statements.py
codat_lending/httpclient.py
codat_lending/invoices.py
codat_lending/journal_entries.py
codat_lending/journals.py
codat_lending/liabilities.py
codat_lending/loan_writeback.py
codat_lending/locations.py
codat_lending/manage_data.py
codat_lending/manage_reports.py
codat_lending/metrics.py
codat_lending/models/__init__.py
codat_lending-10.2.0.dist-info/METADATA
codat_lending-10.2.0.dist-info/WHEEL
codat_lending-10.2.0.dist-info/RECORD
